crappy/__init__.py
crappy/__version__.py
crappy/_global.py
crappy/actuator/__init__.py
crappy/actuator/_deprecated.py
crappy/actuator/adafruit_dc_motor_hat.py
crappy/actuator/fake_dc_motor.py
crappy/actuator/fake_stepper_motor.py
crappy/actuator/jvl_mac_140.py
crappy/actuator/kollmorgen_servostar_300.py
crappy/actuator/newport_tra6ppd.py
crappy/actuator/oriental_ard_k.py
crappy/actuator/phidgets_stepper4a.py
crappy/actuator/pololu_tic.py
crappy/actuator/schneider_mdrive_23.py
crappy/actuator/ft232h/__init__.py
crappy/actuator/ft232h/adafruit_dc_motor_hat.py
crappy/actuator/meta_actuator/__init__.py
crappy/actuator/meta_actuator/actuator.py
crappy/actuator/meta_actuator/meta_actuator.py
crappy/blocks/__init__.py
crappy/blocks/_deprecated.py
crappy/blocks/auto_drive_video_extenso.py
crappy/blocks/button.py
crappy/blocks/camera.py
crappy/blocks/canvas.py
crappy/blocks/client_server.py
crappy/blocks/dashboard.py
crappy/blocks/dic_ve.py
crappy/blocks/dis_correl.py
crappy/blocks/fake_machine.py
crappy/blocks/generator.py
crappy/blocks/gpu_correl.py
crappy/blocks/gpu_ve.py
crappy/blocks/grapher.py
crappy/blocks/hdf_recorder.py
crappy/blocks/ioblock.py
crappy/blocks/link_reader.py
crappy/blocks/machine.py
crappy/blocks/mean.py
crappy/blocks/multiplexer.py
crappy/blocks/pause.py
crappy/blocks/pid.py
crappy/blocks/recorder.py
crappy/blocks/sink.py
crappy/blocks/stop_block.py
crappy/blocks/stop_button.py
crappy/blocks/synchronizer.py
crappy/blocks/ucontroller.py
crappy/blocks/video_extenso.py
crappy/blocks/camera_processes/__init__.py
crappy/blocks/camera_processes/camera_process.py
crappy/blocks/camera_processes/dic_ve.py
crappy/blocks/camera_processes/dis_correl.py
crappy/blocks/camera_processes/display.py
crappy/blocks/camera_processes/gpu_correl.py
crappy/blocks/camera_processes/gpu_ve.py
crappy/blocks/camera_processes/record.py
crappy/blocks/camera_processes/video_extenso.py
crappy/blocks/generator_path/__init__.py
crappy/blocks/generator_path/conditional.py
crappy-2.0.7.dist-info/LICENSE
crappy-2.0.7.dist-info/METADATA
crappy-2.0.7.dist-info/WHEEL
crappy-2.0.7.dist-info/top_level.txt
crappy-2.0.7.dist-info/RECORD
