Metadata-Version: 2.1
Name: crappy
Version: 2.0.7
Summary: Command and Real-time Acquisition in Parallelized Python
Author-email: LaMcube <antoine.weisrock1@centralelille.fr>
Maintainer-email: Antoine Weisrock <antoine.weisrock@gmail.com>
License:                     GNU GENERAL PUBLIC LICENSE
Project-URL: Homepage, https://github.com/LaboratoireMecaniqueLille/crappy
Project-URL: Documentation, https://crappy.readthedocs.io/en/latest/index.html
Project-URL: Repository, https://github.com/LaboratoireMecaniqueLille/crappy.git
Project-URL: Issues, https://github.com/LaboratoireMecaniqueLille/crappy/issues
Project-URL: Download, https://pypi.org/project/crappy/#files
Keywords: control,command,acquisition,multiprocessing
Classifier: Development Status :: 4 - Beta 
Classifier: Intended Audience :: Science/Research
Classifier: License :: OSI Approved :: GNU General Public License v2 or later (GPLv2+)
Classifier: Natural Language :: English
Classifier: Operating System :: OS Independent
Classifier: Programming Language :: Python :: 3.9
Classifier: Programming Language :: Python :: 3.10
Classifier: Programming Language :: Python :: 3.11
Classifier: Programming Language :: Python :: 3.12
Classifier: Programming Language :: Python :: 3.13
Classifier: Topic :: Scientific/Engineering
Classifier: Topic :: Software Development :: Build Tools
Classifier: Topic :: Software Development :: Embedded Systems
Requires-Python: >=3.9
License-File: LICENSE
Requires-Dist: numpy
Provides-Extra: sbc
Requires-Dist: smbus2; extra == "sbc"
Requires-Dist: spidev; extra == "sbc"
Requires-Dist: Adafruit-Blinka; extra == "sbc"
Requires-Dist: adafruit-circuitpython-ads1x15; extra == "sbc"
Requires-Dist: adafruit-circuitpython-motorkit; extra == "sbc"
Requires-Dist: adafruit-circuitpython-mprls; extra == "sbc"
Requires-Dist: adafruit-circuitpython-busdevice; extra == "sbc"
Provides-Extra: image
Requires-Dist: opencv-python>=4.0; extra == "image"
Requires-Dist: Pillow>=8.0.0; extra == "image"
Requires-Dist: matplotlib>=3.3.0; extra == "image"
Requires-Dist: SimpleITK>=2.0.0; extra == "image"
Requires-Dist: scikit-image>=0.18.0; extra == "image"
Provides-Extra: hardware
Requires-Dist: pyusb>=1.1.0; extra == "hardware"
Requires-Dist: pyserial>=3.4; extra == "hardware"
Requires-Dist: pyyaml>=5.3; extra == "hardware"
Provides-Extra: main
Requires-Dist: matplotlib>=3.3.0; extra == "main"
Requires-Dist: opencv-python>=4.0; extra == "main"
Requires-Dist: pyserial>=3.4; extra == "main"
